setup.py
botchallenge/__init__.py
botchallenge/blocktypes.py
botchallenge/client.py
botchallenge/robot.py
botchallenge/robot_test.py
botchallenge.egg-info/PKG-INFO
botchallenge.egg-info/SOURCES.txt
botchallenge.egg-info/dependency_links.txt
botchallenge.egg-info/requires.txt
botchallenge.egg-info/top_level.txt
botchallenge/api/__init__.py
botchallenge/api/materials_pb2.py
botchallenge/api/robotapi_pb2.py
botchallenge/api/storage_pb2.py
google/__init__.py
google/protobuf/__init__.py
google/protobuf/descriptor.py
google/protobuf/descriptor_database.py
google/protobuf/descriptor_pb2.py
google/protobuf/descriptor_pool.py
google/protobuf/message.py
google/protobuf/message_factory.py
google/protobuf/reflection.py
google/protobuf/service.py
google/protobuf/service_reflection.py
google/protobuf/symbol_database.py
google/protobuf/text_encoding.py
google/protobuf/text_format.py
google/protobuf/unittest_custom_options_pb2.py
google/protobuf/unittest_import_pb2.py
google/protobuf/unittest_import_public_pb2.py
google/protobuf/unittest_mset_pb2.py
google/protobuf/unittest_no_generic_services_pb2.py
google/protobuf/unittest_pb2.py
google/protobuf/compiler/__init__.py
google/protobuf/compiler/plugin_pb2.py
google/protobuf/internal/__init__.py
google/protobuf/internal/api_implementation.py
google/protobuf/internal/api_implementation_default_test.py
google/protobuf/internal/containers.py
google/protobuf/internal/cpp_message.py
google/protobuf/internal/decoder.py
google/protobuf/internal/descriptor_database_test.py
google/protobuf/internal/descriptor_pool_test.py
google/protobuf/internal/descriptor_pool_test1_pb2.py
google/protobuf/internal/descriptor_pool_test2_pb2.py
google/protobuf/internal/descriptor_python_test.py
google/protobuf/internal/descriptor_test.py
google/protobuf/internal/encoder.py
google/protobuf/internal/enum_type_wrapper.py
google/protobuf/internal/factory_test1_pb2.py
google/protobuf/internal/factory_test2_pb2.py
google/protobuf/internal/generator_test.py
google/protobuf/internal/message_factory_python_test.py
google/protobuf/internal/message_factory_test.py
google/protobuf/internal/message_listener.py
