Metadata-Version: 1.1
Name: botchallenge
Version: 1.2.0
Summary: A Python API for interacting with a Minecraft server plugin to control a bot.
Home-page: https://github.com/katharosada/botchallenge
Author: Katie Bell
Author-email: katie@katharos.id.au
License: MIT
Keywords: minecraft bot
Platform: UNKNOWN
Classifier: Development Status :: 3 - Alpha
Classifier: Intended Audience :: Developers
Classifier: Intended Audience :: Education
Classifier: License :: OSI Approved :: MIT License
Classifier: Natural Language :: English
Classifier: Programming Language :: Python :: 3
Classifier: Programming Language :: Python :: 3.3
Classifier: Programming Language :: Python :: 3.4
Classifier: Topic :: Games/Entertainment
